ShynaCreatecredentials/Shcreatecredentials.py
ShynaCreatecredentials/__init__.py
ShynaCreatecredentials-0.1.dist-info/LICENSE
ShynaCreatecredentials-0.1.dist-info/METADATA
ShynaCreatecredentials-0.1.dist-info/WHEEL
ShynaCreatecredentials-0.1.dist-info/top_level.txt
ShynaCreatecredentials-0.1.dist-info/RECORD
