Metadata-Version: 2.1
Name: ShynaCreatecredentials
Version: 0.1
Summary: We will be able to create a .ini file and .key file which can be used to store and read the secret keys/password
Home-page: UNKNOWN
Author: Shivam Sharma
Author-email: shivamsharma1913@gmail.com
License: UNKNOWN
Platform: UNKNOWN
License-File: LICENSE
Requires-Dist: cryptography
Requires-Dist: setuptools
Requires-Dist: wheel
